{
    "Symbol": "ASML",
    "AssetType": "Common Stock",
    "Name": "ASML Holding NV ADR",
    "Description": "ASML Holding NV develops, produces, markets, sells and services advanced semiconductor equipment systems consisting of lithography, metrology and inspection related systems for memory and logic chip manufacturers. The company is headquartered in Veldhoven, the Netherlands.",
    "CIK": "937966",
    "Exchange": "NASDAQ",
    "Currency": "USD",
    "Country": "USA",
    "Sector": "TECHNOLOGY",
    "Industry": "SPECIAL INDUSTRY MACHINERY, NEC",
    "Address": "DE RUN 6501, DR VELDHOVEN, NL",
    "FiscalYearEnd": "December",
    "LatestQuarter": "2022-09-30",
    "MarketCapitalization": "273619141000",
    "EBITDA": "7084300000",
    "PERatio": "42.55",
    "PEGRatio": "1.703",
    "BookValue": "22.48",
    "DividendPerShare": "0",
    "DividendYield": "0.0153",
    "EPS": "15.36",
    "RevenuePerShareTTM": "53.24",
    "ProfitMargin": "0.266",
    "OperatingMarginTTM": "0.307",
    "ReturnOnAssetsTTM": "0.122",
    "ReturnOnEquityTTM": "0.594",
    "RevenueTTM": "21173400000",
    "GrossProfitTTM": "10700100000",
    "DilutedEPSTTM": "15.36",
    "QuarterlyEarningsGrowthYOY": "0.056",
    "QuarterlyRevenueGrowthYOY": "0.29",
    "AnalystTargetPrice": "747.45",
    "TrailingPE": "42.55",
    "ForwardPE": "30.49",
    "PriceToSalesRatioTTM": "12.43",
    "PriceToBookRatio": "29.61",
    "EVToRevenue": "12.62",
    "EVToEBITDA": "35.86",
    "Beta": "1.193",
    "52WeekHigh": "706.24",
    "52WeekLow": "362.22",
    "50DayMovingAverage": "604.63",
    "200DayMovingAverage": "533.66",
    "SharesOutstanding": "403138000",
    "DividendDate": "2023-05-10",
    "ExDividendDate": "2023-02-06"
}